vpnkillswitch/__init__.py
vpnkillswitch/systemipswitches.py
vpnkillswitch/vpnkillswitch.py
vpnkillswitch-0.1.11.dist-info/LICENCE
vpnkillswitch-0.1.11.dist-info/METADATA
vpnkillswitch-0.1.11.dist-info/WHEEL
vpnkillswitch-0.1.11.dist-info/entry_points.txt
vpnkillswitch-0.1.11.dist-info/top_level.txt
vpnkillswitch-0.1.11.dist-info/RECORD
