Metadata-Version: 2.1
Name: vpnkillswitch
Version: 0.1.11
Summary: A vpnkillswitch helper from rexbytes.com
Author-email: Good Boy <pythonic@rexbytes.com>
Project-URL: Homepage, https://github.com/RexBytes/vpnkillswitch
Project-URL: Bug Tracker, https://github.com/RexBytes/vpnkillswitch/issues
Project-URL: Download URL, https://github.com/RexBytes/vpnkillswitch/archive/refs/tags/v0.1.11.tar.gz
Classifier: Programming Language :: Python :: 3
Classifier: License :: OSI Approved :: MIT License
Classifier: Operating System :: POSIX :: Linux
Requires-Python: >=3.7
License-File: LICENCE
